etwfe/__init__.py
etwfe/core.py
etwfe/py.typed
etwfe-0.1.4.dist-info/METADATA
etwfe-0.1.4.dist-info/WHEEL
etwfe-0.1.4.dist-info/licenses/LICENSE
etwfe-0.1.4.dist-info/RECORD
