Metadata-Version: 2.4
Name: etwfe
Version: 0.1.4
Summary: Extended Two-Way Fixed Effects estimator (Wooldridge 2021, 2023) for Python
Project-URL: Homepage, https://github.com/armandkapllani/etwfe.html
Project-URL: Documentation, https://armandkapllani.github.io/etwfe.html
Project-URL: Repository, https://github.com/armandkapllani/etwfe
Project-URL: Issues, https://github.com/armandkapllani/etwfe/issues
Project-URL: Changelog, https://github.com/armandkapllani/etwfe/releases
Author: Armand Kapllani
License: MIT
License-File: LICENSE
Keywords: causal-inference,did,difference-in-differences,econometrics,etwfe,fixed-effects,panel-data,treatment-effects,wooldridge
Classifier: Development Status :: 4 - Beta
Classifier: Intended Audience :: Science/Research
Classifier: License :: OSI Approved :: MIT License
Classifier: Operating System :: OS Independent
Classifier: Programming Language :: Python :: 3
Classifier: Programming Language :: Python :: 3.9
Classifier: Programming Language :: Python :: 3.10
Classifier: Programming Language :: Python :: 3.11
Classifier: Programming Language :: Python :: 3.12
Classifier: Topic :: Scientific/Engineering :: Information Analysis
Classifier: Topic :: Scientific/Engineering :: Mathematics
Requires-Python: >=3.10
Requires-Dist: matplotlib>=3.4.0
Requires-Dist: numpy>=1.21.0
Requires-Dist: pandas>=1.3.0
Requires-Dist: pyfixest>=0.18.0
Provides-Extra: dev
Requires-Dist: black>=23.0.0; extra == 'dev'
Requires-Dist: mypy>=1.0.0; extra == 'dev'
Requires-Dist: pandas-stubs>=2.0.0; extra == 'dev'
Requires-Dist: pytest-cov>=4.0.0; extra == 'dev'
Requires-Dist: pytest>=7.0.0; extra == 'dev'
Requires-Dist: ruff>=0.1.0; extra == 'dev'
Provides-Extra: full
Requires-Dist: patsy>=0.5.3; extra == 'full'
Requires-Dist: scipy>=1.7.0; extra == 'full'
